ninjakiwi_api/API/BTD6/__init__.py
ninjakiwi_api/API/BTD6/function.py
ninjakiwi_api/API/BTDB2/__init__.py
ninjakiwi_api/API/BTDB2/function.py
ninjakiwi_api/API/__init__.py
ninjakiwi_api/FUNCTIONS/ERROR/__init__.py
ninjakiwi_api/FUNCTIONS/ERROR/function.py
ninjakiwi_api/FUNCTIONS/FETCH/__init__.py
ninjakiwi_api/FUNCTIONS/FETCH/function.py
ninjakiwi_api/FUNCTIONS/FETCH/model.py
ninjakiwi_api/FUNCTIONS/__init__.py
ninjakiwi_api/__init__.py
ninjakiwi_api/main.py
ninjakiwi_api-1.3.2.dist-info/LICENSE
ninjakiwi_api-1.3.2.dist-info/METADATA
ninjakiwi_api-1.3.2.dist-info/WHEEL
ninjakiwi_api-1.3.2.dist-info/RECORD
