Metadata-Version: 2.1
Name: ninjakiwi-api
Version: 1.3.2
Summary: NinjaKiwi API (Open Data) for Python! (My first library)
Home-page: https://github.com/GustavoSchip/ninjakiwi-api
License: MIT
Keywords: API,NinjaKiwi
Author: Gustavo Schip
Author-email: gustavoschip@proton.me
Maintainer: Gustavo Schip
Maintainer-email: gustavoschip@proton.me
Requires-Python: >=3.11,<4.0.0
Classifier: Development Status :: 4 - Beta
Classifier: Intended Audience :: Developers
Classifier: License :: OSI Approved :: MIT License
Classifier: Natural Language :: English
Classifier: Programming Language :: Python :: 3
Classifier: Programming Language :: Python :: 3.11
Provides-Extra: dev
Provides-Extra: test
Requires-Dist: aiohttp (>=3.8.1,<4.0.0)
Requires-Dist: asyncio (>=3.4.3,<4.0.0)
Requires-Dist: black (>=22.3,<24.0) ; extra == "test"
Requires-Dist: flake8 (==6.1.0) ; extra == "test"
Requires-Dist: flake8-docstrings (>=1.6.0,<2.0.0) ; extra == "test"
Requires-Dist: isort (==5.12.0) ; extra == "test"
Requires-Dist: livereload (>=2.6.3,<3.0.0)
Requires-Dist: pip (>=22.0.3,<24.0.0) ; extra == "dev"
Requires-Dist: pre-commit (>=2.17,<4.0) ; extra == "dev"
Requires-Dist: pyreadline (>=2.1,<3.0)
Requires-Dist: pytest (>=7.0.1,<8.0.0) ; extra == "test"
Requires-Dist: pytest-asyncio (>=0.21.1,<0.22.0) ; extra == "test"
Requires-Dist: pytest-cov (>=3,<5) ; extra == "test"
Requires-Dist: pytest-mock (>=3.11.1,<4.0.0) ; extra == "test"
Requires-Dist: toml (>=0.10.2,<0.11.0) ; extra == "dev"
Requires-Dist: tornado (>=6.2,<7.0)
Requires-Dist: tox (>=3.24.5,<5.0.0) ; extra == "dev"
Requires-Dist: twine (>=3.8,<5.0) ; extra == "dev"
Requires-Dist: virtualenv (>=20.13.1,<21.0.0) ; extra == "dev"
